twcmanager_client/__init__.py
twcmanager_client/client.py
twcmanager_client-0.4.0.dist-info/LICENSE
twcmanager_client-0.4.0.dist-info/METADATA
twcmanager_client-0.4.0.dist-info/WHEEL
twcmanager_client-0.4.0.dist-info/top_level.txt
twcmanager_client-0.4.0.dist-info/RECORD
