Metadata-Version: 2.1
Name: twcmanager-client
Version: 0.4.0
Summary: A simple client for communicating with TWCManager
Home-page: https://github.com/jherby2k/twcmanager-client
Author: Jeremy Herbison
Author-email: jeremy.herbison@gmail.com
License: UNKNOWN
Project-URL: Bug Tracker, https://github.com/jherby2k/twcmanager-client/issues
Platform: UNKNOWN
Classifier: Intended Audience :: Developers
Classifier: Programming Language :: Python :: 3
Classifier: Programming Language :: Python :: 3.7
Classifier: Programming Language :: Python :: 3.8
Classifier: Programming Language :: Python :: 3.9
Classifier: License :: OSI Approved :: Apache Software License
Classifier: Operating System :: OS Independent
Classifier: Topic :: Home Automation
Requires-Python: >=3.7
License-File: LICENSE
Requires-Dist: aiohttp (>=3.7.3)
